dockscribe/__init__.py
dockscribe/__main__.py
dockscribe/config.py
dockscribe/composeCraft/__init__.py
dockscribe/composeCraft/cli.py
dockscribe/composeCraft/server.py
dockscribe/composeCraft/utils.py
dockscribe/container/__init__.py
dockscribe/container/analyse.py
dockscribe/container/cli.py
dockscribe/container/utils.py
dockscribe-1.0.2.dist-info/LICENSE
dockscribe-1.0.2.dist-info/METADATA
dockscribe-1.0.2.dist-info/WHEEL
dockscribe-1.0.2.dist-info/entry_points.txt
dockscribe-1.0.2.dist-info/top_level.txt
dockscribe-1.0.2.dist-info/RECORD
