Metadata-Version: 2.1
Name: dockscribe
Version: 1.0.2
Summary: Turn any docker infrastructure in a visual map with composecraft.com
Author-email: Lucas Sovre <lucas.sovre@entrecompetents.fr>
License:                                  Apache License
Project-URL: Homepage, https://github.com/LucasSovre/dockscribe
Project-URL: Source, https://github.com/LucasSovre/dockscribe
Requires-Python: >=3.9
License-File: LICENSE
Requires-Dist: typer
Requires-Dist: docker
Requires-Dist: requests
Requires-Dist: pyyaml
